Workbook

Sheet Instrucciones
A1: Tecno Cedro S.A.S. – Cuaderno de trabajo, Fase 1 (noviembre de 2026)
A2: NIT P-0009 | Tu proveedor del anillo: Conexión Andes S.A.S. (NIT P-0012) | Tu cliente del anillo: Digital Ceiba S.A.S. (NIT P-0010)
A4: Cómo se trabaja
A5: 1. Mira la hoja Agenda: son las compras, ventas y devoluciones del mes con tu proveedor y tu cliente del anillo.
A6: 2. Diligencia los formatos (celdas amarillas): Orden_Compra, Entrada_Almacen, Comprobante_Egreso, NC_Recibida, Factura_Venta, Remision, Recibo_Caja y NC_Emitida.
A7: 3. Lleva el Kardex_A y el Kardex_B con promedio ponderado, en orden de fecha. La primera fila (gris) ya trae lo comprado al proveedor externo.
A8: 4. Registra TODOS los asientos de noviembre en Libro_Diario, también los de la Fase 0 (los 15 documentos del PDF). Usa el Catalogo de cuentas.
A9: 5. Las columnas Control dicen OK o Revisar. Solo revisan la aritmética (subtotal, IVA, total, saldos y que cada asiento cuadre); la corrección completa la hace el profesor.
A11: Colores
A12: Amarillo = lo diligencias tú. Gris = dato dado o fórmula de control.
A14: Reglas del ejercicio
A15: Todas las empresas del anillo compran y venden al precio de lista. IVA 19% sobre la base. Contado = se paga o cobra por Caja (1105). Crédito = 30 días (Proveedores 2205 / Clientes 1305).
... A20: Todos los datos son ficticios. Documento de práctica, sin valor fiscal.

Sheet Ruta_4_horas
A1: Ruta sugerida para el taller de 4 horas
A3: Tiempo | B3: Qué haces | C3: Hojas | D3: Obligatorio
A4: 0:00 – 0:15 | B4: Lee la ficha de tu empresa (PDF) y la hoja Agenda. | C4: Instrucciones, Agenda | D4: Sí
A5: 0:15 – 1:15 | B5: Fase 0: registra en el Libro_Diario los asientos de los 15 documentos del PDF. | C5: Libro_Diario, Catalogo | D5: Sí
A6: 1:15 – 2:30 | B6: Fase 1: lleva el Kardex y registra compras, ventas y devoluciones con tu anillo. Los formatos (orden de compra, factura de venta, etc.) se diligencian según indique el profesor. | C6: Agenda, Kardex_A, Kardex_B, Libro_Diario; formatos opcionales | D6: Kardex y asientos: sí. Formatos: según tiempo
A7: 2:30 – 3:00 | B7: Cierre del mes: conciliación bancaria, ajuste de toma física, nómina y depreciación. | C7: Conciliacion, Nomina, Depreciacion, Libro_Diario | D7: Sí
A8: 3:00 – 3:40 | B8: Revisa que todo cuadre: IVA, Mayor, Balance de prueba y Estados financieros (se calculan solos). Corrige asientos descuadrados. | C8: IVA_Periodo, Mayor, Balance_Prueba, Estados | D8: Sí
A9: 3:40 – 4:00 | B9: Entrega tu cuaderno al profesor y revisión conjunta. | C9: — | D9: Sí
A11: Meta: que Balance_Prueba y Estados digan OK al final. Si algo da Revisar, busca el asiento que no cuadra.

Sheet Agenda
A1: Operación | B1: Tipo | C1: Fecha | D1: Contraparte | E1: NIT | F1: Código | G1: Producto | H1: Cantidad | I1: Valor unitario (sin IVA) | J1: Condición | K1: N° de factura o nota | L1: Factura afectada
A2: C1 | B2: Compra | C2: 46335 | D2: Conexión Andes S.A.S. | E2: P-0012 | F2: TEC-002 | G2: Teclado USB estándar | H2: 13 | I2: 46800 | J2: contado | K2: FV-A12-001 | L2: —
A3: C2 | B3: Compra | C3: 46337 | D3: Conexión Andes S.A.S. | E3: P-0012 | F3: TEC-001 | G3: Mouse óptico USB | H3: 27 | I3: 23400 | J3: contado | K3: FV-A12-002 | L3: —
A4: V1 | B4: Venta | C4: 46338 | D4: Digital Ceiba S.A.S. | E4: P-0010 | F4: TEC-002 | G4: Teclado USB estándar | H4: 13 | I4: 46800 | J4: contado | K4: FV-A09-001 | L4: —
A5: C3 | B5: Compra | C5: 46339 | D5: Conexión Andes S.A.S. | E5: P-0012 | F5: TEC-001 | G5: Mouse óptico USB | H5: 11 | I5: 23400 | J5: crédito | K5: FV-A12-003 | L5: —
A6: C4 | B6: Compra | C6: 46342 | D6: Conexión Andes S.A.S. | E6: P-0012 | F6: TEC-002 | G6: Teclado USB estándar | H6: 11 | I6: 46800 | J6: contado | K6: FV-A12-004 | L6: —
A7: V2 | B7: Venta | C7: 46343 | D7: Digital Ceiba S.A.S. | E7: P-0010 | F7: TEC-001 | G7: Mouse óptico USB | H7: 27 | I7: 23400 | J7: contado | K7: FV-A09-002 | L7: —
A8: C5 | B8: Compra | C8: 46344 | D8: Conexión Andes S.A.S. | E8: P-0012 | F8: TEC-001 | G8: Mouse óptico USB | H8: 10 | I8: 23400 | J8: crédito | K8: FV-A12-005 | L8: —
A9: V3 | B9: Venta | C9: 46345 | D9: Digital Ceiba S.A.S. | E9: P-0010 | F9: TEC-001 | G9: Mouse óptico USB | H9: 11 | I9: 23400 | J9: crédito | K9: FV-A09-003 | L9: —
A10: C6 | B10: Compra | C10: 46346 | D10: Conexión Andes S.A.S. | E10: P-0012 | F10: TEC-001 | G10: Mouse óptico USB | H10: 11 | I10: 23400 | J10: crédito | K10: FV-A12-006 | L10: —
A11: V4 | B11: Venta | C11: 46349 | D11: Digital Ceiba S.A.S. | E11: P-0010 | F11: TEC-002 | G11: Teclado USB estándar | H11: 11 | I11: 46800 | J11: contado | K11: FV-A09-004 | L11: —
A12: V5 | B12: Venta | C12: 46350 | D12: Digital Ceiba S.A.S. | E12: P-0010 | F12: TEC-001 | G12: Mouse óptico USB | H12: 10 | I12: 23400 | J12: crédito | K12: FV-A09-005 | L12: —
A13: DV | B13: Devolución en ventas (el cliente te devuelve) | C13: 46351 | D13: Digital Ceiba S.A.S. | E13: P-0010 | F13: TEC-001 | G13: Mouse óptico USB | H13: 2 | I13: 23400 | J13: — | K13: NC-A09-001 | L13: FV-A09-003
... A15: DC | B15: Devolución en compras (tú devuelves) | C15: 46353 | D15: Conexión Andes S.A.S. | E15: P-0012 | F15: TEC-001 | G15: Mouse óptico USB | H15: 2 | I15: 23400 | J15: — | K15: NC-A12-001 | L15: FV-A12-003
A17: Compra: tu proveedor del anillo te factura. Venta: tú facturas a tu cliente con el número indicado. Las operaciones siguen el orden de las fechas.

Sheet Orden_Compra
A1: Operación | B1: Fecha | C1: N° orden | D1: Proveedor | E1: NIT | F1: Código | G1: Cantidad | H1: Valor unitario | I1: Subtotal | J1: IVA 19% | K1: Total | L1: Condición de pago | M1: Control
A2: C1 | M2: =IF(OR(I2="",J2="",K2=""),"",IF(AND(J2=ROUND(I2*Parametros!$B$2,0),K2=I2+J2,I2=G2*H2),"OK","Revisar"))
A3: C2 | M3: =IF(OR(I3="",J3="",K3=""),"",IF(AND(J3=ROUND(I3*Parametros!$B$2,0),K3=I3+J3,I3=G3*H3),"OK","Revisar"))
A4: C3 | M4: =IF(OR(I4="",J4="",K4=""),"",IF(AND(J4=ROUND(I4*Parametros!$B$2,0),K4=I4+J4,I4=G4*H4),"OK","Revisar"))
A5: C4 | M5: =IF(OR(I5="",J5="",K5=""),"",IF(AND(J5=ROUND(I5*Parametros!$B$2,0),K5=I5+J5,I5=G5*H5),"OK","Revisar"))
A6: C5 | M6: =IF(OR(I6="",J6="",K6=""),"",IF(AND(J6=ROUND(I6*Parametros!$B$2,0),K6=I6+J6,I6=G6*H6),"OK","Revisar"))
A7: C6 | M7: =IF(OR(I7="",J7="",K7=""),"",IF(AND(J7=ROUND(I7*Parametros!$B$2,0),K7=I7+J7,I7=G7*H7),"OK","Revisar"))

Sheet Entrada_Almacen
A1: Operación | B1: Fecha | C1: N° entrada | D1: N° orden de compra | E1: N° factura proveedor | F1: Código | G1: Cantidad recibida | H1: Valor unitario | I1: Valor total | J1: Control
A2: C1 | J2: =IF(OR(G2="",H2="",I2=""),"",IF(I2=G2*H2,"OK","Revisar"))
A3: C2 | J3: =IF(OR(G3="",H3="",I3=""),"",IF(I3=G3*H3,"OK","Revisar"))
A4: C3 | J4: =IF(OR(G4="",H4="",I4=""),"",IF(I4=G4*H4,"OK","Revisar"))
A5: C4 | J5: =IF(OR(G5="",H5="",I5=""),"",IF(I5=G5*H5,"OK","Revisar"))
A6: C5 | J6: =IF(OR(G6="",H6="",I6=""),"",IF(I6=G6*H6,"OK","Revisar"))
A7: C6 | J7: =IF(OR(G7="",H7="",I7=""),"",IF(I7=G7*H7,"OK","Revisar"))

Sheet Comprobante_Egreso
A1: Operación | B1: Fecha | C1: N° comprobante | D1: Beneficiario | E1: Concepto (N° factura) | F1: Valor base | G1: IVA | H1: Valor pagado | I1: Medio de pago | J1: Control
A2: C1 | J2: =IF(OR(F2="",G2="",H2=""),"",IF(AND(G2=ROUND(F2*Parametros!$B$2,0),H2=F2+G2),"OK","Revisar"))
A3: C2 | J3: =IF(OR(F3="",G3="",H3=""),"",IF(AND(G3=ROUND(F3*Parametros!$B$2,0),H3=F3+G3),"OK","Revisar"))
A4: C4 | J4: =IF(OR(F4="",G4="",H4=""),"",IF(AND(G4=ROUND(F4*Parametros!$B$2,0),H4=F4+G4),"OK","Revisar"))

Sheet NC_Recibida
A1: Operación | B1: Fecha | C1: N° nota crédito | D1: Proveedor | E1: Factura afectada | F1: Código | G1: Cantidad devuelta | H1: Valor unitario | I1: Subtotal | J1: IVA 19% | K1: Total | L1: Control
A2: DC | L2: =IF(OR(I2="",J2="",K2=""),"",IF(AND(J2=ROUND(I2*Parametros!$B$2,0),K2=I2+J2,I2=G2*H2),"OK","Revisar"))

Sheet Factura_Venta
A1: Operación | B1: Fecha | C1: N° factura | D1: Cliente | E1: NIT | F1: Código | G1: Cantidad | H1: Valor unitario | I1: Subtotal | J1: IVA 19% | K1: Total | L1: Forma de pago | M1: Control
A2: V1 | M2: =IF(OR(I2="",J2="",K2=""),"",IF(AND(J2=ROUND(I2*Parametros!$B$2,0),K2=I2+J2,I2=G2*H2),"OK","Revisar"))
A3: V2 | M3: =IF(OR(I3="",J3="",K3=""),"",IF(AND(J3=ROUND(I3*Parametros!$B$2,0),K3=I3+J3,I3=G3*H3),"OK","Revisar"))
A4: V3 | M4: =IF(OR(I4="",J4="",K4=""),"",IF(AND(J4=ROUND(I4*Parametros!$B$2,0),K4=I4+J4,I4=G4*H4),"OK","Revisar"))
A5: V4 | M5: =IF(OR(I5="",J5="",K5=""),"",IF(AND(J5=ROUND(I5*Parametros!$B$2,0),K5=I5+J5,I5=G5*H5),"OK","Revisar"))
A6: V5 | M6: =IF(OR(I6="",J6="",K6=""),"",IF(AND(J6=ROUND(I6*Parametros!$B$2,0),K6=I6+J6,I6=G6*H6),"OK","Revisar"))
A7: V6 | M7: =IF(OR(I7="",J7="",K7=""),"",IF(AND(J7=ROUND(I7*Parametros!$B$2,0),K7=I7+J7,I7=G7*H7),"OK","Revisar"))

Sheet Remision
A1: Operación | B1: Fecha | C1: N° remisión | D1: N° factura | E1: Cliente | F1: Código | G1: Cantidad despachada | H1: Control
A2: V1 | H2: =IF(G2="","",IF(AND(ISNUMBER(G2),G2>0),"OK","Revisar"))
A3: V2 | H3: =IF(G3="","",IF(AND(ISNUMBER(G3),G3>0),"OK","Revisar"))
A4: V3 | H4: =IF(G4="","",IF(AND(ISNUMBER(G4),G4>0),"OK","Revisar"))
A5: V4 | H5: =IF(G5="","",IF(AND(ISNUMBER(G5),G5>0),"OK","Revisar"))
A6: V5 | H6: =IF(G6="","",IF(AND(ISNUMBER(G6),G6>0),"OK","Revisar"))
A7: V6 | H7: =IF(G7="","",IF(AND(ISNUMBER(G7),G7>0),"OK","Revisar"))

Sheet Recibo_Caja
A1: Operación | B1: Fecha | C1: N° recibo | D1: Recibido de | E1: Concepto (N° factura) | F1: Valor base | G1: IVA | H1: Valor recibido | I1: Forma | J1: Control
A2: V1 | J2: =IF(OR(F2="",G2="",H2=""),"",IF(AND(G2=ROUND(F2*Parametros!$B$2,0),H2=F2+G2),"OK","Revisar"))
A3: V2 | J3: =IF(OR(F3="",G3="",H3=""),"",IF(AND(G3=ROUND(F3*Parametros!$B$2,0),H3=F3+G3),"OK","Revisar"))
A4: V4 | J4: =IF(OR(F4="",G4="",H4=""),"",IF(AND(G4=ROUND(F4*Parametros!$B$2,0),H4=F4+G4),"OK","Revisar"))

Sheet NC_Emitida
A1: Operación | B1: Fecha | C1: N° nota crédito | D1: Cliente | E1: Factura afectada | F1: Código | G1: Cantidad devuelta | H1: Valor unitario | I1: Subtotal | J1: IVA 19% | K1: Total | L1: Control
A2: DV | L2: =IF(OR(I2="",J2="",K2=""),"",IF(AND(J2=ROUND(I2*Parametros!$B$2,0),K2=I2+J2,I2=G2*H2),"OK","Revisar"))

Sheet Kardex_A
A1: Fecha | B1: Documento | C1: Detalle | D1: Entrada cant. | E1: Entrada v. unit. | F1: Entrada valor | G1: Salida cant. | H1: Salida v. unit. | I1: Salida valor | J1: Saldo cant. | K1: Saldo v. unit. | L1: Saldo valor | M1: Control
A2: 46330 | B2: FV-P-0033 | C2: Compra al proveedor externo (Fase 0) | D2: 195 | E2: 18000 | F2: 3510000 | J2: 195 | K2: 18000 | L2: 3510000 | M2: inicio
M3: =IF(J3="","",IF(AND(J3=J2+N(D3)-N(G3),L3=L2+N(F3)-N(I3),J3>=0),"OK","Revisar"))
M4: =IF(J4="","",IF(AND(J4=J3+N(D4)-N(G4),L4=L3+N(F4)-N(I4),J4>=0),"OK","Revisar"))
M5: =IF(J5="","",IF(AND(J5=J4+N(D5)-N(G5),L5=L4+N(F5)-N(I5),J5>=0),"OK","Revisar"))
M6: =IF(J6="","",IF(AND(J6=J5+N(D6)-N(G6),L6=L5+N(F6)-N(I6),J6>=0),"OK","Revisar"))
M7: =IF(J7="","",IF(AND(J7=J6+N(D7)-N(G7),L7=L6+N(F7)-N(I7),J7>=0),"OK","Revisar"))
M8: =IF(J8="","",IF(AND(J8=J7+N(D8)-N(G8),L8=L7+N(F8)-N(I8),J8>=0),"OK","Revisar"))
M9: =IF(J9="","",IF(AND(J9=J8+N(D9)-N(G9),L9=L8+N(F9)-N(I9),J9>=0),"OK","Revisar"))
M10: =IF(J10="","",IF(AND(J10=J9+N(D10)-N(G10),L10=L9+N(F10)-N(I10),J10>=0),"OK","Revisar"))
M11: =IF(J11="","",IF(AND(J11=J10+N(D11)-N(G11),L11=L10+N(F11)-N(I11),J11>=0),"OK","Revisar"))
M12: =IF(J12="","",IF(AND(J12=J11+N(D12)-N(G12),L12=L11+N(F12)-N(I12),J12>=0),"OK","Revisar"))
M13: =IF(J13="","",IF(AND(J13=J12+N(D13)-N(G13),L13=L12+N(F13)-N(I13),J13>=0),"OK","Revisar"))
M14: =IF(J14="","",IF(AND(J14=J13+N(D14)-N(G14),L14=L13+N(F14)-N(I14),J14>=0),"OK","Revisar"))
... M20: =IF(J20="","",IF(AND(J20=J19+N(D20)-N(G20),L20=L19+N(F20)-N(I20),J20>=0),"OK","Revisar"))
A22: TEC-001 – Mouse óptico USB. Registra las operaciones en orden de fecha y termina con el ajuste de la toma física del 30/11/2026.

Sheet Kardex_B
A1: Fecha | B1: Documento | C1: Detalle | D1: Entrada cant. | E1: Entrada v. unit. | F1: Entrada valor | G1: Salida cant. | H1: Salida v. unit. | I1: Salida valor | J1: Saldo cant. | K1: Saldo v. unit. | L1: Saldo valor | M1: Control
A2: 46332 | B2: FV-P-0034 | C2: Compra al proveedor externo (Fase 0) | D2: 105 | E2: 36000 | F2: 3780000 | J2: 105 | K2: 36000 | L2: 3780000 | M2: inicio
M3: =IF(J3="","",IF(AND(J3=J2+N(D3)-N(G3),L3=L2+N(F3)-N(I3),J3>=0),"OK","Revisar"))
M4: =IF(J4="","",IF(AND(J4=J3+N(D4)-N(G4),L4=L3+N(F4)-N(I4),J4>=0),"OK","Revisar"))
M5: =IF(J5="","",IF(AND(J5=J4+N(D5)-N(G5),L5=L4+N(F5)-N(I5),J5>=0),"OK","Revisar"))
M6: =IF(J6="","",IF(AND(J6=J5+N(D6)-N(G6),L6=L5+N(F6)-N(I6),J6>=0),"OK","Revisar"))
M7: =IF(J7="","",IF(AND(J7=J6+N(D7)-N(G7),L7=L6+N(F7)-N(I7),J7>=0),"OK","Revisar"))
M8: =IF(J8="","",IF(AND(J8=J7+N(D8)-N(G8),L8=L7+N(F8)-N(I8),J8>=0),"OK","Revisar"))
M9: =IF(J9="","",IF(AND(J9=J8+N(D9)-N(G9),L9=L8+N(F9)-N(I9),J9>=0),"OK","Revisar"))
M10: =IF(J10="","",IF(AND(J10=J9+N(D10)-N(G10),L10=L9+N(F10)-N(I10),J10>=0),"OK","Revisar"))
M11: =IF(J11="","",IF(AND(J11=J10+N(D11)-N(G11),L11=L10+N(F11)-N(I11),J11>=0),"OK","Revisar"))
M12: =IF(J12="","",IF(AND(J12=J11+N(D12)-N(G12),L12=L11+N(F12)-N(I12),J12>=0),"OK","Revisar"))
M13: =IF(J13="","",IF(AND(J13=J12+N(D13)-N(G13),L13=L12+N(F13)-N(I13),J13>=0),"OK","Revisar"))
M14: =IF(J14="","",IF(AND(J14=J13+N(D14)-N(G14),L14=L13+N(F14)-N(I14),J14>=0),"OK","Revisar"))
... M20: =IF(J20="","",IF(AND(J20=J19+N(D20)-N(G20),L20=L19+N(F20)-N(I20),J20>=0),"OK","Revisar"))
A22: TEC-002 – Teclado USB estándar. Registra las operaciones en orden de fecha y termina con el ajuste de la toma física del 30/11/2026.

Sheet Libro_Diario
A1: N° asiento | B1: Fecha | C1: Documento soporte | D1: Código cuenta | E1: Nombre de la cuenta | F1: Débito | G1: Crédito | H1: Control del asiento | J1: Total débitos | K1: =SUM(F2:F221)
H2: =IF(A2="","",IF(SUMIFS($F$2:$F$221,$A$2:$A$221,A2)=SUMIFS($G$2:$G$221,$A$2:$A$221,A2),"OK","Descuadrado")) | J2: Total créditos | K2: =SUM(G2:G221)
H3: =IF(A3="","",IF(SUMIFS($F$2:$F$221,$A$2:$A$221,A3)=SUMIFS($G$2:$G$221,$A$2:$A$221,A3),"OK","Descuadrado")) | J3: Diferencia | K3: =K1-K2
H4: =IF(A4="","",IF(SUMIFS($F$2:$F$221,$A$2:$A$221,A4)=SUMIFS($G$2:$G$221,$A$2:$A$221,A4),"OK","Descuadrado"))
H5: =IF(A5="","",IF(SUMIFS($F$2:$F$221,$A$2:$A$221,A5)=SUMIFS($G$2:$G$221,$A$2:$A$221,A5),"OK","Descuadrado"))
H6: =IF(A6="","",IF(SUMIFS($F$2:$F$221,$A$2:$A$221,A6)=SUMIFS($G$2:$G$221,$A$2:$A$221,A6),"OK","Descuadrado"))
H7: =IF(A7="","",IF(SUMIFS($F$2:$F$221,$A$2:$A$221,A7)=SUMIFS($G$2:$G$221,$A$2:$A$221,A7),"OK","Descuadrado"))
H8: =IF(A8="","",IF(SUMIFS($F$2:$F$221,$A$2:$A$221,A8)=SUMIFS($G$2:$G$221,$A$2:$A$221,A8),"OK","Descuadrado"))
H9: =IF(A9="","",IF(SUMIFS($F$2:$F$221,$A$2:$A$221,A9)=SUMIFS($G$2:$G$221,$A$2:$A$221,A9),"OK","Descuadrado"))
H10: =IF(A10="","",IF(SUMIFS($F$2:$F$221,$A$2:$A$221,A10)=SUMIFS($G$2:$G$221,$A$2:$A$221,A10),"OK","Descuadrado"))
H11: =IF(A11="","",IF(SUMIFS($F$2:$F$221,$A$2:$A$221,A11)=SUMIFS($G$2:$G$221,$A$2:$A$221,A11),"OK","Descuadrado"))
H12: =IF(A12="","",IF(SUMIFS($F$2:$F$221,$A$2:$A$221,A12)=SUMIFS($G$2:$G$221,$A$2:$A$221,A12),"OK","Descuadrado"))
H13: =IF(A13="","",IF(SUMIFS($F$2:$F$221,$A$2:$A$221,A13)=SUMIFS($G$2:$G$221,$A$2:$A$221,A13),"OK","Descuadrado"))
H14: =IF(A14="","",IF(SUMIFS($F$2:$F$221,$A$2:$A$221,A14)=SUMIFS($G$2:$G$221,$A$2:$A$221,A14),"OK","Descuadrado"))
H15: =IF(A15="","",IF(SUMIFS($F$2:$F$221,$A$2:$A$221,A15)=SUMIFS($G$2:$G$221,$A$2:$A$221,A15),"OK","Descuadrado"))
... H221: =IF(A221="","",IF(SUMIFS($F$2:$F$221,$A$2:$A$221,A221)=SUMIFS($G$2:$G$221,$A$2:$A$221,A221),"OK","Descuadrado"))

Sheet Catalogo
A1: Código | B1: Cuenta
A2: 1105 | B2: Caja
A3: 1110 | B3: Bancos
A4: 1305 | B4: Clientes nacionales
A5: 1435 | B5: Mercancías no fabricadas por la empresa
A6: 1528 | B6: Equipo de computación y comunicacion
A7: 1592 | B7: Depreciación acumulada
A8: 2205 | B8: Proveedores nacionales
A9: 2370 | B9: Retenciones y aportes de nómina
A10: 2408 | B10: Impuesto sobre las ventas por pagar (IVA)
A11: 2505 | B11: Salarios por pagar
A12: 3105 | B12: Capital suscrito y pagado
A13: 4135 | B13: Ingresos por ventas
... A25: 6135 | B25: Costo de ventas

Sheet Conciliacion
A1: Conciliación bancaria – 30 de noviembre de 2026
A2: Compara el extracto con tu cuenta Bancos (1110) y concilia las partidas.
A4: Saldo final según el extracto bancario
A5: Saldo según tus libros (1110) ANTES de registrar cuota de manejo, GMF e intereses
A6: (−) Cuota de manejo cobrada por el banco
A7: (−) GMF 4 x 1000 cobrado por el banco
A8: (+) Intereses abonados por el banco
A9: Saldo conciliado de libros | C9: =IF(B9="","",IF(B9=B5-B6-B7+B8,"OK","Revisar"))
A10: Diferencia con el extracto (debe ser 0) | C10: =IF(B10="","",IF(AND(B10=B9-B4,B10=0),"OK","Revisar"))
A11: Saldo de la cuenta 1110 en tu Libro_Diario (automático) | B11: =SUMIFS(Libro_Diario!$F$2:$F$221,Libro_Diario!$D$2:$D$221,1110)-SUMIFS(Libro_Diario!$G$2:$G$221,Libro_Diario!$D$2:$D$221,1110) | C11: =IF(B11=B4,"OK","Revisar")
A13: El último control compara tu libro diario con el extracto: da OK cuando ya registraste la cuota de manejo, el GMF y los intereses.

Sheet Nomina
A1: Liquidación de nómina – noviembre de 2026
A2: Mes completo (30 días). Solo aportes del empleado: salud 4% y pensión 4%. Sin auxilio de transporte, aportes del empleador ni prestaciones.
A4: Trabajador
A5: Cargo
A6: Salario mensual (tomado del contrato)
A7: Días liquidados | C7: =IF(B7="","",IF(B7=30,"OK","Revisar"))
A8: Aporte de salud del empleado (4%) | C8: =IF(B8="","",IF(B8=ROUND(B6*Parametros!$B$3,0),"OK","Revisar"))
A9: Aporte de pensión del empleado (4%) | C9: =IF(B9="","",IF(B9=ROUND(B6*Parametros!$B$4,0),"OK","Revisar"))
A10: Total deducciones | C10: =IF(B10="","",IF(B10=B8+B9,"OK","Revisar"))
A11: Neto a pagar al trabajador | C11: =IF(B11="","",IF(B11=B6-B10,"OK","Revisar"))
A13: El asiento de la nómina va en el Libro_Diario: gasto de personal contra retenciones y aportes de nómina y salarios por pagar.

Sheet Depreciacion
A1: Depreciación del equipo de cómputo – línea recta
A2: El activo se deprecia por un mes completo en noviembre (convención del ejercicio).
A4: Costo del activo (cuenta 1528, con el IVA como mayor valor)
A5: Vida útil (meses) | C5: =IF(B5="","",IF(B5=36,"OK","Revisar"))
A6: Valor residual
A7: Depreciación mensual = (costo − residual) ÷ vida útil | C7: =IF(B7="","",IF(B7=ROUND((B4-B6)/B5,0),"OK","Revisar"))
A8: Meses depreciados en noviembre | C8: =IF(B8="","",IF(B8=1,"OK","Revisar"))
A9: Depreciación acumulada al 30/11/2026 | C9: =IF(B9="","",IF(B9=B7*B8,"OK","Revisar"))
A10: Valor en libros = costo − depreciación acumulada | C10: =IF(B10="","",IF(B10=B4-B9,"OK","Revisar"))

Sheet IVA_Periodo
A1: IVA del periodo (automático desde tu Libro_Diario)
A2: Cuenta 2408: los débitos son IVA de compras (descontable) y los créditos IVA de ventas (generado).
A4: IVA generado en ventas (créditos de 2408) | B4: =SUMIFS(Libro_Diario!$G$2:$G$221,Libro_Diario!$D$2:$D$221,2408)
A5: IVA descontable en compras (débitos de 2408) | B5: =SUMIFS(Libro_Diario!$F$2:$F$221,Libro_Diario!$D$2:$D$221,2408)
A6: Saldo (generado − descontable) | B6: =B4-B5
A7: Resultado | B7: =IF(B6>0,"IVA por pagar",IF(B6<0,"Saldo a favor","Sin saldo"))
A10: Las devoluciones (notas crédito) ya reducen el IVA en tus asientos.

Sheet Mayor
A1: Libro mayor – resumen por cuenta (automático)
A2: Se calcula solo con lo que registres en Libro_Diario.
A3: Código | B3: Cuenta | C3: Total débitos | D3: Total créditos | E3: Saldo deudor | F3: Saldo acreedor
A4: 1105 | B4: Caja | C4: =SUMIFS(Libro_Diario!$F$2:$F$221,Libro_Diario!$D$2:$D$221,A4) | D4: =SUMIFS(Libro_Diario!$G$2:$G$221,Libro_Diario!$D$2:$D$221,A4) | E4: =MAX(C4-D4,0) | F4: =MAX(D4-C4,0)
A5: 1110 | B5: Bancos | C5: =SUMIFS(Libro_Diario!$F$2:$F$221,Libro_Diario!$D$2:$D$221,A5) | D5: =SUMIFS(Libro_Diario!$G$2:$G$221,Libro_Diario!$D$2:$D$221,A5) | E5: =MAX(C5-D5,0) | F5: =MAX(D5-C5,0)
A6: 1305 | B6: Clientes nacionales | C6: =SUMIFS(Libro_Diario!$F$2:$F$221,Libro_Diario!$D$2:$D$221,A6) | D6: =SUMIFS(Libro_Diario!$G$2:$G$221,Libro_Diario!$D$2:$D$221,A6) | E6: =MAX(C6-D6,0) | F6: =MAX(D6-C6,0)
A7: 1435 | B7: Mercancías no fabricadas por la empresa | C7: =SUMIFS(Libro_Diario!$F$2:$F$221,Libro_Diario!$D$2:$D$221,A7) | D7: =SUMIFS(Libro_Diario!$G$2:$G$221,Libro_Diario!$D$2:$D$221,A7) | E7: =MAX(C7-D7,0) | F7: =MAX(D7-C7,0)
A8: 1528 | B8: Equipo de computación y comunicacion | C8: =SUMIFS(Libro_Diario!$F$2:$F$221,Libro_Diario!$D$2:$D$221,A8) | D8: =SUMIFS(Libro_Diario!$G$2:$G$221,Libro_Diario!$D$2:$D$221,A8) | E8: =MAX(C8-D8,0) | F8: =MAX(D8-C8,0)
A9: 1592 | B9: Depreciación acumulada | C9: =SUMIFS(Libro_Diario!$F$2:$F$221,Libro_Diario!$D$2:$D$221,A9) | D9: =SUMIFS(Libro_Diario!$G$2:$G$221,Libro_Diario!$D$2:$D$221,A9) | E9: =MAX(C9-D9,0) | F9: =MAX(D9-C9,0)
A10: 2205 | B10: Proveedores nacionales | C10: =SUMIFS(Libro_Diario!$F$2:$F$221,Libro_Diario!$D$2:$D$221,A10) | D10: =SUMIFS(Libro_Diario!$G$2:$G$221,Libro_Diario!$D$2:$D$221,A10) | E10: =MAX(C10-D10,0) | F10: =MAX(D10-C10,0)
A11: 2370 | B11: Retenciones y aportes de nómina | C11: =SUMIFS(Libro_Diario!$F$2:$F$221,Libro_Diario!$D$2:$D$221,A11) | D11: =SUMIFS(Libro_Diario!$G$2:$G$221,Libro_Diario!$D$2:$D$221,A11) | E11: =MAX(C11-D11,0) | F11: =MAX(D11-C11,0)
A12: 2408 | B12: Impuesto sobre las ventas por pagar (IVA) | C12: =SUMIFS(Libro_Diario!$F$2:$F$221,Libro_Diario!$D$2:$D$221,A12) | D12: =SUMIFS(Libro_Diario!$G$2:$G$221,Libro_Diario!$D$2:$D$221,A12) | E12: =MAX(C12-D12,0) | F12: =MAX(D12-C12,0)
A13: 2505 | B13: Salarios por pagar | C13: =SUMIFS(Libro_Diario!$F$2:$F$221,Libro_Diario!$D$2:$D$221,A13) | D13: =SUMIFS(Libro_Diario!$G$2:$G$221,Libro_Diario!$D$2:$D$221,A13) | E13: =MAX(C13-D13,0) | F13: =MAX(D13-C13,0)
A14: 3105 | B14: Capital suscrito y pagado | C14: =SUMIFS(Libro_Diario!$F$2:$F$221,Libro_Diario!$D$2:$D$221,A14) | D14: =SUMIFS(Libro_Diario!$G$2:$G$221,Libro_Diario!$D$2:$D$221,A14) | E14: =MAX(C14-D14,0) | F14: =MAX(D14-C14,0)
A15: 4135 | B15: Ingresos por ventas | C15: =SUMIFS(Libro_Diario!$F$2:$F$221,Libro_Diario!$D$2:$D$221,A15) | D15: =SUMIFS(Libro_Diario!$G$2:$G$221,Libro_Diario!$D$2:$D$221,A15) | E15: =MAX(C15-D15,0) | F15: =MAX(D15-C15,0)
... A27: 6135 | B27: Costo de ventas | C27: =SUMIFS(Libro_Diario!$F$2:$F$221,Libro_Diario!$D$2:$D$221,A27) | D27: =SUMIFS(Libro_Diario!$G$2:$G$221,Libro_Diario!$D$2:$D$221,A27) | E27: =MAX(C27-D27,0) | F27: =MAX(D27-C27,0)
B28: TOTALES | C28: =SUM(C4:C27) | D28: =SUM(D4:D27) | E28: =SUM(E4:E27) | F28: =SUM(F4:F27)
B29: Control | C29: =IF(AND(C28=D28,E28=F28),"OK","Revisar")

Sheet Balance_Prueba
A1: Balance de prueba al 30 de noviembre de 2026 (automático)
A3: Código | B3: Cuenta | C3: Débito | D3: Crédito
A4: =Mayor!A4 | B4: =Mayor!B4 | C4: =Mayor!E4 | D4: =Mayor!F4
A5: =Mayor!A5 | B5: =Mayor!B5 | C5: =Mayor!E5 | D5: =Mayor!F5
A6: =Mayor!A6 | B6: =Mayor!B6 | C6: =Mayor!E6 | D6: =Mayor!F6
A7: =Mayor!A7 | B7: =Mayor!B7 | C7: =Mayor!E7 | D7: =Mayor!F7
A8: =Mayor!A8 | B8: =Mayor!B8 | C8: =Mayor!E8 | D8: =Mayor!F8
A9: =Mayor!A9 | B9: =Mayor!B9 | C9: =Mayor!E9 | D9: =Mayor!F9
A10: =Mayor!A10 | B10: =Mayor!B10 | C10: =Mayor!E10 | D10: =Mayor!F10
A11: =Mayor!A11 | B11: =Mayor!B11 | C11: =Mayor!E11 | D11: =Mayor!F11
A12: =Mayor!A12 | B12: =Mayor!B12 | C12: =Mayor!E12 | D12: =Mayor!F12
A13: =Mayor!A13 | B13: =Mayor!B13 | C13: =Mayor!E13 | D13: =Mayor!F13
A14: =Mayor!A14 | B14: =Mayor!B14 | C14: =Mayor!E14 | D14: =Mayor!F14
A15: =Mayor!A15 | B15: =Mayor!B15 | C15: =Mayor!E15 | D15: =Mayor!F15
... A27: =Mayor!A27 | B27: =Mayor!B27 | C27: =Mayor!E27 | D27: =Mayor!F27
B28: SUMAS IGUALES | C28: =SUM(C4:C27) | D28: =SUM(D4:D27)
B29: Control | C29: =IF(C28=D28,"OK","Revisar")

Sheet Estados
A1: Tecno Cedro S.A.S. – Estados financieros al 30 de noviembre de 2026 (automáticos)
A4: ESTADO DE RESULTADOS
A5: Ingresos por ventas (4135) | B5: =(SUMIFS(Mayor!$F$4:$F$27,Mayor!$A$4:$A$27,4135)-SUMIFS(Mayor!$E$4:$E$27,Mayor!$A$4:$A$27,4135))
A6: (−) Devoluciones en ventas (4175) | B6: =(SUMIFS(Mayor!$E$4:$E$27,Mayor!$A$4:$A$27,4175)-SUMIFS(Mayor!$F$4:$F$27,Mayor!$A$4:$A$27,4175))
A7: Ventas netas | B7: =B5-B6
A8: (−) Costo de ventas (6135) | B8: =(SUMIFS(Mayor!$E$4:$E$27,Mayor!$A$4:$A$27,6135)-SUMIFS(Mayor!$F$4:$F$27,Mayor!$A$4:$A$27,6135))
A9: UTILIDAD BRUTA | B9: =B7-B8
A10: Gastos de personal (5105) | B10: =(SUMIFS(Mayor!$E$4:$E$27,Mayor!$A$4:$A$27,5105)-SUMIFS(Mayor!$F$4:$F$27,Mayor!$A$4:$A$27,5105))
A11: Arrendamientos (5120) | B11: =(SUMIFS(Mayor!$E$4:$E$27,Mayor!$A$4:$A$27,5120)-SUMIFS(Mayor!$F$4:$F$27,Mayor!$A$4:$A$27,5120))
A12: Servicios (5135) | B12: =(SUMIFS(Mayor!$E$4:$E$27,Mayor!$A$4:$A$27,5135)-SUMIFS(Mayor!$F$4:$F$27,Mayor!$A$4:$A$27,5135))
A13: Mantenimiento y reparaciones (5145) | B13: =(SUMIFS(Mayor!$E$4:$E$27,Mayor!$A$4:$A$27,5145)-SUMIFS(Mayor!$F$4:$F$27,Mayor!$A$4:$A$27,5145))
A14: Depreciaciones (5160) | B14: =(SUMIFS(Mayor!$E$4:$E$27,Mayor!$A$4:$A$27,5160)-SUMIFS(Mayor!$F$4:$F$27,Mayor!$A$4:$A$27,5160))
A15: Impuestos – GMF (5115) | B15: =(SUMIFS(Mayor!$E$4:$E$27,Mayor!$A$4:$A$27,5115)-SUMIFS(Mayor!$F$4:$F$27,Mayor!$A$4:$A$27,5115))
A16: Diversos (5195) | B16: =(SUMIFS(Mayor!$E$4:$E$27,Mayor!$A$4:$A$27,5195)-SUMIFS(Mayor!$F$4:$F$27,Mayor!$A$4:$A$27,5195))
A17: Total gastos operacionales | B17: =SUM(B10:B16)
A18: UTILIDAD OPERACIONAL | B18: =B9-B17
A19: (+) Ingresos financieros (4210) | B19: =(SUMIFS(Mayor!$F$4:$F$27,Mayor!$A$4:$A$27,4210)-SUMIFS(Mayor!$E$4:$E$27,Mayor!$A$4:$A$27,4210))
A20: (+) Ingresos diversos (4295) | B20: =(SUMIFS(Mayor!$F$4:$F$27,Mayor!$A$4:$A$27,4295)-SUMIFS(Mayor!$E$4:$E$27,Mayor!$A$4:$A$27,4295))
A21: (−) Gastos financieros (5305) | B21: =(SUMIFS(Mayor!$E$4:$E$27,Mayor!$A$4:$A$27,5305)-SUMIFS(Mayor!$F$4:$F$27,Mayor!$A$4:$A$27,5305))
A22: UTILIDAD NETA DEL PERIODO (sin impuesto de renta) | B22: =B18+B19+B20-B21
A24: BALANCE GENERAL
A25: Caja (1105) | B25: =(SUMIFS(Mayor!$E$4:$E$27,Mayor!$A$4:$A$27,1105)-SUMIFS(Mayor!$F$4:$F$27,Mayor!$A$4:$A$27,1105))
A26: Bancos (1110) | B26: =(SUMIFS(Mayor!$E$4:$E$27,Mayor!$A$4:$A$27,1110)-SUMIFS(Mayor!$F$4:$F$27,Mayor!$A$4:$A$27,1110))
A27: Clientes (1305) | B27: =(SUMIFS(Mayor!$E$4:$E$27,Mayor!$A$4:$A$27,1305)-SUMIFS(Mayor!$F$4:$F$27,Mayor!$A$4:$A$27,1305))
A28: Inventarios (1435) | B28: =(SUMIFS(Mayor!$E$4:$E$27,Mayor!$A$4:$A$27,1435)-SUMIFS(Mayor!$F$4:$F$27,Mayor!$A$4:$A$27,1435))
A29: IVA a favor (saldo deudor de 2408) | B29: =SUMIFS(Mayor!$E$4:$E$27,Mayor!$A$4:$A$27,2408)
A30: Equipo de computación (1528) | B30: =(SUMIFS(Mayor!$E$4:$E$27,Mayor!$A$4:$A$27,1528)-SUMIFS(Mayor!$F$4:$F$27,Mayor!$A$4:$A$27,1528))
A31: (−) Depreciación acumulada (1592) | B31: =(SUMIFS(Mayor!$F$4:$F$27,Mayor!$A$4:$A$27,1592)-SUMIFS(Mayor!$E$4:$E$27,Mayor!$A$4:$A$27,1592))
A32: TOTAL ACTIVOS | B32: =SUM(B25:B30)-B31
A33: Proveedores (2205) | B33: =(SUMIFS(Mayor!$F$4:$F$27,Mayor!$A$4:$A$27,2205)-SUMIFS(Mayor!$E$4:$E$27,Mayor!$A$4:$A$27,2205))
A34: Retenciones y aportes de nómina (2370) | B34: =(SUMIFS(Mayor!$F$4:$F$27,Mayor!$A$4:$A$27,2370)-SUMIFS(Mayor!$E$4:$E$27,Mayor!$A$4:$A$27,2370))
A35: Salarios por pagar (2505) | B35: =(SUMIFS(Mayor!$F$4:$F$27,Mayor!$A$4:$A$27,2505)-SUMIFS(Mayor!$E$4:$E$27,Mayor!$A$4:$A$27,2505))
A36: IVA por pagar (saldo acreedor de 2408) | B36: =SUMIFS(Mayor!$F$4:$F$27,Mayor!$A$4:$A$27,2408)
A37: TOTAL PASIVOS | B37: =SUM(B33:B36)
A38: Capital (3105) | B38: =(SUMIFS(Mayor!$F$4:$F$27,Mayor!$A$4:$A$27,3105)-SUMIFS(Mayor!$E$4:$E$27,Mayor!$A$4:$A$27,3105))
A39: Utilidad del periodo | B39: =B22
A40: TOTAL PATRIMONIO | B40: =B38+B39
A41: TOTAL PASIVOS + PATRIMONIO | B41: =B37+B40
A42: Control: activos = pasivos + patrimonio | B42: =IF(B32=B41,"OK","Revisar")

Sheet Parametros
A1: Parámetro | B1: Valor
A2: Tarifa IVA | B2: 0.19
A3: Aporte salud del empleado | B3: 0.04
A4: Aporte pensión del empleado | B4: 0.04
